{
  "image_path": "eng_ans2.jpg",
  "accuracy": 23.333333333333332,
  "correct_count": 7,
  "detected_answers": {
    "1": "BLANK",
    "2": "B",
    "3": "A",
    "4": "BLANK",
    "5": "BLANK",
    "6": "BLANK",
    "7": "A",
    "8": "BLANK",
    "9": "B",
    "10": "BLANK",
    "11": "BLANK",
    "12": "D",
    "13": "D",
    "14": "BLANK",
    "15": "BLANK",
    "16": "BLANK",
    "17": "D",
    "18": "D",
    "19": "D",
    "20": "BLANK",
    "21": "BLANK",
    "22": "B",
    "23": "BLANK",
    "24": "BLANK",
    "25": "BLANK",
    "26": "BLANK",
    "27": "BLANK",
    "28": "A",
    "29": "B",
    "30": "BLANK"
  },
  "manual_coordinates_used": true
}